aio_adb_shell/__init__.py
aio_adb_shell/adb_device.py
aio_adb_shell/adb_message.py
aio_adb_shell/constants.py
aio_adb_shell/exceptions.py
aio_adb_shell/auth/__init__.py
aio_adb_shell/auth/keygen.py
aio_adb_shell/auth/sign_cryptography.py
aio_adb_shell/auth/sign_pycryptodome.py
aio_adb_shell/auth/sign_pythonrsa.py
aio_adb_shell/handle/__init__.py
aio_adb_shell/handle/base_handle.py
aio_adb_shell/handle/tcp_handle.py
aio_adb_shell-0.0.1.dist-info/LICENSE
aio_adb_shell-0.0.1.dist-info/METADATA
aio_adb_shell-0.0.1.dist-info/WHEEL
aio_adb_shell-0.0.1.dist-info/top_level.txt
aio_adb_shell-0.0.1.dist-info/RECORD
