Metadata-Version: 2.1
Name: aio-adb-shell
Version: 0.0.1
Summary: A Python implementation of ADB with shell and FileSync functionality.
Home-page: https://github.com/JeffLIrion/aio_adb_shell
Author: Jeff Irion
Author-email: jefflirion@users.noreply.github.com
License: UNKNOWN
Keywords: adb,android
Platform: UNKNOWN
Classifier: Operating System :: OS Independent
Classifier: License :: OSI Approved :: Apache Software License
Classifier: Programming Language :: Python :: 3
Requires-Python: >=3.6
Requires-Dist: cryptography
Requires-Dist: pyasn1
Requires-Dist: rsa
